LICENSE
README.md
setup.py
coinmarketcap_scraper/__init__.py
coinmarketcap_scraper.egg-info/PKG-INFO
coinmarketcap_scraper.egg-info/SOURCES.txt
coinmarketcap_scraper.egg-info/dependency_links.txt
coinmarketcap_scraper.egg-info/requires.txt
coinmarketcap_scraper.egg-info/top_level.txt