Metadata-Version: 2.1
Name: coinmarketcap-scraper
Version: 1.0.0
Summary: A python library to scrape on Coin Market Scraper
Home-page: UNKNOWN
Author: DataKund
Author-email: datakund@gmail.com
License: Apache License 2.0
Keywords: coin market scraper python bot_studio automation search address review date
Platform: UNKNOWN
License-File: LICENSE
